apolloMusicRipper/config.py
apolloMusicRipper/run.py
apolloMusicRipper-0.1.dist-info/DESCRIPTION.rst
apolloMusicRipper-0.1.dist-info/METADATA
apolloMusicRipper-0.1.dist-info/RECORD
apolloMusicRipper-0.1.dist-info/WHEEL
apolloMusicRipper-0.1.dist-info/metadata.json
apolloMusicRipper-0.1.dist-info/top_level.txt
