Metadata-Version: 2.0
Name: apolloMusicRipper
Version: 0.1
Summary: The ripper and tagger for Apollo
Home-page: https://github.com/ebber/apolloRipper
Author: Erik Beitel
Author-email: erik.beitel@gmail.com
License: UNKNOWN
Download-URL: https://github.com/ebber/apolloMusicRipper/archive/0.1.tar.gz
Keywords: audio,youtube ripper
Platform: UNKNOWN
Requires-Dist: logging
Requires-Dist: youtube-dl
